strawberrypy/__init__.py
strawberrypy/scene.py
strawberrypy/shapes.py
strawberrypy-0.0.5.dist-info/LICENSE
strawberrypy-0.0.5.dist-info/METADATA
strawberrypy-0.0.5.dist-info/WHEEL
strawberrypy-0.0.5.dist-info/top_level.txt
strawberrypy-0.0.5.dist-info/RECORD
