Metadata-Version: 2.1
Name: strawberrypy
Version: 0.0.5
Summary: Graphical animation module.
Home-page: https://github.com/Spatial-Innovations/strawberrypy
Author: Spatial Innovations
Author-email: spatialinnovations@gmail.com
License: UNKNOWN
Platform: UNKNOWN
Classifier: Programming Language :: Python :: 3
Classifier: License :: OSI Approved :: GNU General Public License v2 or later (GPLv2+)
Classifier: Operating System :: OS Independent
Requires-Dist: Pillow
Requires-Dist: numpy
Requires-Dist: opencv-python
Requires-Dist: pygame
